clinicedc_tests/__init__.py
clinicedc_tests/action_items.py
clinicedc_tests/admin.py
clinicedc_tests/admin_site.py
clinicedc_tests/apps.py
clinicedc_tests/baker_recipes.py
clinicedc_tests/config/__init__.py
clinicedc_tests/config/default_test_settings.py
clinicedc_tests/config/func_main.py
clinicedc_tests/config/get_installed_apps_for_tests.py
clinicedc_tests/consents.py
clinicedc_tests/dummy_panel.py
clinicedc_tests/eligibility.py
clinicedc_tests/etc/django_crypto_fields
clinicedc_tests/etc/user-aes-local.key
clinicedc_tests/etc/user-aes-restricted.key
clinicedc_tests/etc/user-rsa-local-private.pem
clinicedc_tests/etc/user-rsa-local-public.pem
clinicedc_tests/etc/user-rsa-restricted-private.pem
clinicedc_tests/etc/user-rsa-restricted-public.pem
clinicedc_tests/etc/user-salt-local.key
clinicedc_tests/etc/user-salt-restricted.key
clinicedc_tests/faker.py
clinicedc_tests/form_labels.py
clinicedc_tests/forms.py
clinicedc_tests/helper.py
clinicedc_tests/holidays.csv
clinicedc_tests/holidays_extra_mozambique.csv
clinicedc_tests/label_templates/aliquot.lbl
clinicedc_tests/label_templates/box.lbl
clinicedc_tests/label_templates/manifest.lbl
clinicedc_tests/label_templates/requisition.lbl
clinicedc_tests/labs.py
clinicedc_tests/list_data/__init__.py
clinicedc_tests/list_data/bad_list_data.py
clinicedc_tests/list_data/bad_list_data2.py
clinicedc_tests/list_data/bad_list_data3.py
clinicedc_tests/list_data/dup_list_data.py
clinicedc_tests/list_data/list_data.py
clinicedc_tests/list_data/list_data1.py
clinicedc_tests/list_data/list_data2.py
clinicedc_tests/list_data/list_data_adherence.py
clinicedc_tests/list_data/list_data_with_site.py
clinicedc_tests/list_data/model_data.py
clinicedc_tests/list_data/model_data2.py
clinicedc_tests/list_data/model_data3.py
clinicedc_tests/list_data/model_data4.py
clinicedc_tests/migrations/__init__.py
clinicedc_tests/mixins/__init__.py
clinicedc_tests/mixins/form_validator_test_mixin.py
clinicedc_tests/mixins/site_test_case_mixin.py
clinicedc_tests-1.1.0.dist-info/licenses/LICENSE
clinicedc_tests-1.1.0.dist-info/WHEEL
clinicedc_tests-1.1.0.dist-info/METADATA
clinicedc_tests-1.1.0.dist-info/RECORD
