Metadata-Version: 2.4
Name: clinicedc-tests
Version: 1.1.0
Summary: Shared test config and utils for clinicedc projects and related apps
Keywords: django,clinicedc,edc,clinical trials,research,data management,esource
Author: Erik van Widenfelt, Jonathan Willitts
Author-email: Erik van Widenfelt <ew2789@gmail.com>, Jonathan Willitts <j.willitts@ucl.ac.uk>
License-Expression: GPL-3.0-or-later
License-File: LICENSE
Classifier: Development Status :: 5 - Production/Stable
Classifier: Environment :: Web Environment
Classifier: Framework :: Django
Classifier: Framework :: Django :: 5.2
Classifier: Development Status :: 5 - Production/Stable
Classifier: Intended Audience :: Developers
Classifier: Intended Audience :: Science/Research
Classifier: Operating System :: OS Independent
Classifier: Programming Language :: Python :: 3.12
Classifier: Programming Language :: Python :: 3.13
Requires-Dist: coverage>=7.10.1
Requires-Dist: django-mock-queries>=2.3.0
Requires-Dist: faker>=37.4.2
Requires-Dist: model-bakery>=1.20.5
Requires-Dist: time-machine>=2.16.0
Requires-Dist: tox-uv>=1.26.2
Requires-Dist: tox>=4.32.0
Maintainer: Erik van Widenfelt
Maintainer-email: Erik van Widenfelt <ew2789@gmail.com>
Requires-Python: >=3.12, <3.14
Project-URL: Changelog, https://github.com/clinicedc/clinicedc-tests/blob/main/CHANGES
Project-URL: Documentation, https://github.com/clinicedc/clinicedc-tests/docs
Project-URL: Homepage, https://github.com/clinicedc/clinicedc-tests
Project-URL: Repository, https://github.com/clinicedc/clinicedc-tests.git
